LICENSE
MANIFEST.in
README.rst
setup.py
chainscan/__init__.py
chainscan/_block.py
chainscan/_block_c.cpp
chainscan/_block_c.pxd
chainscan/_block_c.pyx
chainscan/_common_c.cpp
chainscan/_common_c.pxd
chainscan/_common_c.pyx
chainscan/_track_c.cpp
chainscan/_track_c.pyx
chainscan/_tx_c.cpp
chainscan/_tx_c.pxd
chainscan/_tx_c.pyx
chainscan/_utxo.hpp
chainscan/block.py
chainscan/blockchain.py
chainscan/consts.pxi
chainscan/defs.py
chainscan/loggers.py
chainscan/misc.py
chainscan/rawfiles.py
chainscan/scan.py
chainscan/track.py
chainscan/tx.py
chainscan/utils.py
chainscan/version.py
chainscan.egg-info/PKG-INFO
chainscan.egg-info/SOURCES.txt
chainscan.egg-info/dependency_links.txt
chainscan.egg-info/top_level.txt
experimental/__init__.py
experimental/balances.py
experimental/parallel.py