Metadata-Version: 1.0
Name: chainscan
Version: 0.2.1
Summary: Feel the blockchain, one transaction at a time.
Home-page: https://github.com/fungibit/chainscan
Author: fungibit
Author-email: fungibit@yandex.com
License: MIT
Keywords: bitcoin,blockchain,iterator,analysis
Platform: POSIX
Platform: Windows
